temper_core/__init__.py
temper_core/py.typed
temper_core/regex.py
temper_core/testing.py
temper_core-0.6.0.dist-info/METADATA
temper_core-0.6.0.dist-info/WHEEL
temper_core-0.6.0.dist-info/RECORD
