Metadata-Version: 2.4
Name: temper-core
Version: 0.6.0
Summary: Runtime support for Python generated by Temper
Author-email: Temper Authors <libraries@temper.systems>
License: Apache-2.0 OR MIT
Requires-Python: >=3.11
